LICENSE
README.md
setup.cfg
setup.py
ai_commit_msg/__init__.py
ai_commit_msg/main.py
ai_commit_msg/prepare_commit_msg_hook.py
ai_commit_msg/cli/__init__.py
ai_commit_msg/cli/config_handler.py
ai_commit_msg/cli/conventional_commit_handler.py
ai_commit_msg/cli/gen_ai_commit_message_handler.py
ai_commit_msg/cli/help_ai_handler.py
ai_commit_msg/cli/hook_handler.py
ai_commit_msg/cli/summary_handler.py
ai_commit_msg/core/__init__.py
ai_commit_msg/core/gen_commit_msg.py
ai_commit_msg/core/llm_chat_completion.py
ai_commit_msg/core/prompt.py
ai_commit_msg/services/__init__.py
ai_commit_msg/services/anthropic_service.py
ai_commit_msg/services/config_service.py
ai_commit_msg/services/git_service.py
ai_commit_msg/services/husky_service.py
ai_commit_msg/services/llm_service.py
ai_commit_msg/services/llm_service_factory.py
ai_commit_msg/services/local_db_service.py
ai_commit_msg/services/ollama_service.py
ai_commit_msg/services/onboarding_service.py
ai_commit_msg/services/openai_service.py
ai_commit_msg/services/pip_service.py
ai_commit_msg/utils/__init__.py
ai_commit_msg/utils/error.py
ai_commit_msg/utils/git_utils.py
ai_commit_msg/utils/logger.py
ai_commit_msg/utils/models.py
ai_commit_msg/utils/utils.py
git_ai_commit.egg-info/PKG-INFO
git_ai_commit.egg-info/SOURCES.txt
git_ai_commit.egg-info/dependency_links.txt
git_ai_commit.egg-info/entry_points.txt
git_ai_commit.egg-info/requires.txt
git_ai_commit.egg-info/top_level.txt