Metadata-Version: 2.4
Name: git_ai_commit
Version: 1.0.13
Summary: A project to generate commit messages using AI
Home-page: https://github.com/the-cafe/ai-commit-msg
Author: Ming Lin, Seif Mamdouh, Ali Alobaidi
Author-email: minglianglin50@gmail.com, seifmamdouh7878@gmail.com, alinawar2000@gmail.com
License: MIT
Classifier: Programming Language :: Python :: 3
Classifier: License :: OSI Approved :: MIT License
Classifier: Operating System :: OS Independent
Requires-Python: >=3.6
License-File: LICENSE
Requires-Dist: openai
Requires-Dist: requests
Requires-Dist: anthropic
Requires-Dist: rich
Requires-Dist: pyfiglet
Requires-Dist: prompt_toolkit
Requires-Dist: inquirer
Provides-Extra: dev
Requires-Dist: black==24.8.0; extra == "dev"
Dynamic: license-file
